chiku/__init__.py
chiku/chebyshev.py
chiku/fourier.py
chiku/pade.py
chiku/remez.py
chiku/taylor.py
chiku/tf_ann.py
chiku/mpmath/__init__.py
chiku/mpmath/mpchebyshev.py
chiku/mpmath/mpdigits.py
chiku/mpmath/mpfourier.py
chiku/mpmath/mppade.py
chiku/mpmath/mpremez.py
chiku/mpmath/mptaylor.py
chiku-0.0.25.dist-info/LICENSE
chiku-0.0.25.dist-info/METADATA
chiku-0.0.25.dist-info/WHEEL
chiku-0.0.25.dist-info/top_level.txt
chiku-0.0.25.dist-info/RECORD
