Metadata-Version: 2.1
Name: chiku
Version: 0.0.25
Summary: Python package for efficient probabilistic polynomial approximation of arbitrary functions.
Author-email: Devharsh Trivedi <devharsh@live.in>
Project-URL: Homepage, https://github.com/devharsh/chiku/blob/main/README.md
Project-URL: Docs, https://github.com/devharsh/chiku/tree/main/tests
Project-URL: Bug Tracker, https://github.com/devharsh/chiku/issues
Project-URL: repository, https://github.com/devharsh/chiku
Classifier: Programming Language :: Python :: 3
Classifier: License :: OSI Approved :: MIT License
Classifier: Operating System :: OS Independent
Requires-Python: >=3.7
License-File: LICENSE
